myl_discovery-0.6.4.dist-info/licenses/LICENSE
myldiscovery/__init__.py
myldiscovery/__main__.py
myldiscovery/discovery.py
myldiscovery/main.py
myl_discovery-0.6.4.dist-info/METADATA
myl_discovery-0.6.4.dist-info/WHEEL
myl_discovery-0.6.4.dist-info/entry_points.txt
myl_discovery-0.6.4.dist-info/top_level.txt
myl_discovery-0.6.4.dist-info/RECORD
