Metadata-Version: 2.4
Name: myl-discovery
Version: 0.6.4
Summary: email autodiscovery
Author-email: Philipp Schmitt <philipp@schmitt.co>
License:                     GNU GENERAL PUBLIC LICENSE
Project-URL: homepage, https://github.com/pschmitt/myl-discovery
Project-URL: documentation, https://github.com/pschmitt/myl-discovery/blob/head/readme.md
Project-URL: repository, https://github.com/pschmitt/myl-discovery
Project-URL: issues, https://github.com/pschmitt/myl-discovery/issues
Keywords: email-discovery,autodiscover,autoconfig,smtp,imap,email,discovery
Classifier: Programming Language :: Python :: 3
Requires-Python: >=3.8
License-File: LICENSE
Requires-Dist: dnspython<3.0.0,>=2.0.0
Requires-Dist: exchangelib<6.0.0,>=5.0.0
Requires-Dist: requests<3.0.0,>=2.0.0
Requires-Dist: rich<15.0.0,>=13.0.0
Requires-Dist: xmltodict<2.0.0,>=0.13.0
Dynamic: license-file
